one_table/Table.py
one_table/Utils.py
one_table/__init__.py
one_table-1.0.21.dist-info/METADATA
one_table-1.0.21.dist-info/WHEEL
one_table-1.0.21.dist-info/top_level.txt
one_table-1.0.21.dist-info/RECORD
