Metadata-Version: 2.1
Name: one-table
Version: 1.0.21
Summary: Python dynamoDB one table
Author: Gerswin Pineda
Author-email: g3rswin@gmail.com
Keywords: python,dynamodb
Classifier: Development Status :: 3 - Alpha
Classifier: Intended Audience :: Developers
Classifier: Programming Language :: Python :: 3
Classifier: Topic :: Software Development :: Libraries :: Python Modules
Classifier: Topic :: Software Development :: Libraries
Classifier: License :: OSI Approved :: MIT License
Requires-Dist: cerberus
